<odoo>
  <data>
    <record id="helpdesk.helpdesk_ticket_view_form" model="ir.ui.view">
      <field name="model">helpdesk.ticket</field>
      <field name="arch" type="xml">
        <!--vitsa original de odoo 14 
          <form string="Helpdesk Ticket">
              <header>
                  <field name="is_self_assigned" invisible="1"/>
                  <button name="assign_ticket_to_self" string="Assign To Me" type="object" class="oe_highlight" groups="helpdesk.group_helpdesk_user" attrs="{'invisible': [('is_self_assigned', '=', True)]}"/>
                  <field name="stage_id" widget="statusbar" options="{'clickable': '1', 'fold_field': 'fold'}"/>
              </header>
              <sheet>
                  <field name="legend_blocked" invisible="1"/>
                  <field name="legend_normal" invisible="1"/>
                  <field name="legend_done" invisible="1"/>
                  <field name="partner_ticket_count" invisible="1"/>
                  <div class="oe_button_box" name="button_box">
                      <button name="action_get_attachment_tree_view" class="oe_stat_button" icon="fa-book" type="object" attrs="{'invisible':  [('attachment_number', '=', 0)]}">
                          <field name="attachment_number" widget="statinfo" string="Documents"/>
                      </button>
                  </div>
                  <widget name="web_ribbon" title="Archived" bg_color="bg-danger" attrs="{'invisible': [('active', '=', True)]}"/>
                  <field name="kanban_state" widget="state_selection"/>
                  <div class="oe_title">
                      <h1><field name="name" class="field_name" placeholder="Subject..."/></h1>
                      <field name="sla_status_ids" widget="many2many_tags" options="{'color_field': 'color'}" readonly="1" groups="helpdesk.group_use_sla"/>
                  </div>
                  <group>
                      <group>
                          <field name="active" invisible="1"/>
                          <field name="team_id"/>
                          <field name="user_id" class="field_user_id" domain="['&amp;', ('id', 'in', domain_user_ids), ('share', '=', False)]" widget="many2one_avatar_user"/>
                          <field name="domain_user_ids" invisible="1"/>
                          <field name="ticket_type_id"/>
                          <field name="priority" widget="priority"/>
                          <field name="tag_ids" widget="many2many_tags" options="{'color_field': 'color'}"/>
                          <field name="company_id" groups="base.group_multi_company"/>
                          <field name="sla_deadline" attrs="{'invisible': [('sla_deadline', '=', False)]}" groups="helpdesk.group_use_sla"/>
                      </group>
                      <group>
                          <field name="partner_id" class="field_partner_id" domain="['|', ('company_id', '=', False), ('company_id', '=', company_id)]" widget="res_partner_many2one"/>
                          <field name="partner_name" attrs="{'invisible': [('partner_id', '!=', False)]}"/>
                          <field name="partner_email"/>
                          <field name="email_cc" groups="base.group_no_one"/>
                      </group>
                  </group>
                  <field name="description" class="field_description" placeholder="Description of the ticket..."/>
              </sheet>
              <div class="oe_chatter">
                  <field name="message_follower_ids"/>
                  <field name="activity_ids"/>
                  <field name="message_ids" options="{'post_refresh': 'recipients'}"/>
              </div>

          </form>
        -->
        <form string="Helpdesk Ticket"  edit="1" >
          <header>
            <field name="stage_id" widget="statusbar"  attrs="{'readonly': 1}"  />      
          </header>

          <sheet>
            <field name="kanban_state" widget="state_selection" />
                  
            <div class="row">
                <div class="col-sm-4">
                </div>
                <div class="col-sm-4 text-center">
                    <div class="btn-group btn-group-sm" role="group" aria-label="validar opciones">
                        <button name="crearYValidarSolicitudDeToner" effect="{'message':'Exito!','fadeout':'medium'}" string="Crear y validar solicitud de t贸ner (Nueva forma!!!)" type="object" class="oe_highlight"  groups="studio_customization.validar_toner_d61119fe-f670-4dd0-9dee-6d2bfdd1824e" attrs="{'invisible': [ '|', ('stage_id', '=', 18), ('stage_id', '=', 4)] }" />
                    </div>
                </div>
            </div>
            <br/>
            <div class="row">
                <div class="col-sm-12 text-center">
                    <div class="btn-group btn-group-sm" role="group" aria-label="Cmbiar de estados">
                        <button name="cambioCotizacion" string="Cambiar estado a cotizaci贸n" type="object" class="oe_highlight" groups="studio_customization.cambio_cotizacion_co_3157cb27-cdc9-4840-b19d-7f11ad51631a" attrs="{'invisible': [ '|', ('stage_id', '=', 18), ('stage_id', '=', 4)] }" />
                        
                    </div>
                    <div class="btn-group btn-group-sm" role="group" aria-label="Cmbiar de estados">
                        
                        <button name="cerrar_con_comentario_wizard" string="Cerrar ticket" type="object" icon="fa-lock" class="iconDiagnostico"  groups="studio_customization.cerrar_tickets_mesa_41c2145f-10a2-429c-b59d-4cc9ec16d613" attrs="{'invisible': ['|', ('stage_id', '=', 18), ('stage_id', '=', 4)] }" />
                    </div>
                </div>
            </div>
            <br/>
            
            <div class="oe_title">
                <h1>
                    <field name="name" class="field_name" string="Descripci贸n del reporte" placeholder="Descripci贸n del reporte..." widget="text" invisible="1"/>
                </h1>
                <!--<field name="sla_name" class="badge badge-danger oe_inline" attrs="{'invisible': [('sla_active','=',False)]}"/>-->
            </div>

            <group name="tipoDeReporte">
                <group name="tipoDeReporte_left">
                    <field name="ticket_type_id" string="Tipo de vale" invisible="1" />
                    <field name="x_studio_tipo_de_vale" string="Tipo de reporte"  />
                    <field name="x_studio_refticket" string="ticket"  widget="html" />
                    
                </group>
                <group invisible='[["team_id", "!=", 8]]'>
                    <field name='validarHastaAlmacenTicket' />
                    <field name='validarTicket' />
                    <field name='ponerTicketEnEspera' />
                </group>
                
            </group>

        </form>
        

      </field>
    </record>
  </data>
</odoo>